himena_bio/__init__.py
himena_bio/_func.py
himena_bio/_utils.py
himena_bio/consts.py
himena_bio/io.py
himena_bio/tools/__init__.py
himena_bio/tools/_cast.py
himena_bio/tools/align.py
himena_bio/tools/misc.py
himena_bio/tools/translate.py
himena_bio/widgets/__init__.py
himena_bio/widgets/_base.py
himena_bio/widgets/_editor_actions.py
himena_bio/widgets/_editor_control.py
himena_bio/widgets/_feature_view.py
himena_bio/widgets/ab1.py
himena_bio/widgets/alignment.py
himena_bio/widgets/editor.py
himena_bio-0.0.1.dist-info/METADATA
himena_bio-0.0.1.dist-info/WHEEL
himena_bio-0.0.1.dist-info/entry_points.txt
himena_bio-0.0.1.dist-info/licenses/LICENSE
himena_bio-0.0.1.dist-info/RECORD
