Metadata-Version: 2.4
Name: himena-bio
Version: 0.0.1
Summary: Plasmid editor and basic bioinformatic analysis in himena
Project-URL: Documentation, https://github.com/hanjinliu/himena-bio#readme
Project-URL: Issues, https://github.com/hanjinliu/himena-bio/issues
Project-URL: Source, https://github.com/hanjinliu/himena-bio
Author-email: hanjinliu <liuhanjin.sc@gmail.com>
License: BSD 3-Clause License
License-File: LICENSE
Classifier: Development Status :: 4 - Beta
Classifier: Programming Language :: Python
Classifier: Programming Language :: Python :: 3.10
Classifier: Programming Language :: Python :: 3.11
Classifier: Programming Language :: Python :: 3.12
Classifier: Programming Language :: Python :: 3.13
Classifier: Programming Language :: Python :: Implementation :: CPython
Classifier: Programming Language :: Python :: Implementation :: PyPy
Requires-Python: >=3.10
Requires-Dist: biopython>=1.85
Requires-Dist: cmap>=0.5.0
Requires-Dist: himena
Provides-Extra: testing
Requires-Dist: pyqt6; extra == 'testing'
Requires-Dist: pytest-cov>=2.0; extra == 'testing'
Requires-Dist: pytest-qt; extra == 'testing'
Requires-Dist: pytest>=6.0; extra == 'testing'
